LICENSE.txt
MANIFEST.in
README.md
setup.py
charcade/__init__.py
charcade/charcade.py
charcade.egg-info/PKG-INFO
charcade.egg-info/SOURCES.txt
charcade.egg-info/dependency_links.txt
charcade.egg-info/not-zip-safe
charcade.egg-info/top_level.txt
charcade/words_by_letter/a.txt
charcade/words_by_letter/b.txt
charcade/words_by_letter/c.txt
charcade/words_by_letter/d.txt
charcade/words_by_letter/e.txt
charcade/words_by_letter/f.txt
charcade/words_by_letter/g.txt
charcade/words_by_letter/h.txt
charcade/words_by_letter/i.txt
charcade/words_by_letter/j.txt
charcade/words_by_letter/k.txt
charcade/words_by_letter/l.txt
charcade/words_by_letter/m.txt
charcade/words_by_letter/n.txt
charcade/words_by_letter/o.txt
charcade/words_by_letter/p.txt
charcade/words_by_letter/q.txt
charcade/words_by_letter/r.txt
charcade/words_by_letter/s.txt
charcade/words_by_letter/t.txt
charcade/words_by_letter/u.txt
charcade/words_by_letter/v.txt
charcade/words_by_letter/w.txt
charcade/words_by_letter/x.txt
charcade/words_by_letter/y.txt
charcade/words_by_letter/z.txt
charcade/words_by_type/adjectives.txt
charcade/words_by_type/adverbs.txt
charcade/words_by_type/all.txt
charcade/words_by_type/animals.txt
charcade/words_by_type/conjunctions.txt
charcade/words_by_type/countries.txt
charcade/words_by_type/interesting.txt
charcade/words_by_type/interjections.txt
charcade/words_by_type/nouns.txt
charcade/words_by_type/prepositions.txt
charcade/words_by_type/pronouns.txt
charcade/words_by_type/slurs.txt
charcade/words_by_type/space.txt
charcade/words_by_type/verbs.txt