Metadata-Version: 2.1
Name: charcade
Version: 1.0.0
Summary: String manipulation.
Home-page: UNKNOWN
Author: Aaron Clayton
Author-email: ecoahaaron@gmail.com
License: MIT
Keywords: string
Platform: UNKNOWN
Classifier: Development Status :: 5 - Production/Stable
Classifier: Intended Audience :: Developers
Classifier: Operating System :: Microsoft :: Windows :: Windows 10
Classifier: License :: OSI Approved :: MIT License
Classifier: Programming Language :: Python :: 3
License-File: LICENSE.txt
